cue_ml-1.0.0.dist-info/licenses/LICENSE
cuepy/__init__.py
cuepy/__main__.py
cuepy/__version__.py
cuepy/cli.py
cuepy/config.py
cuepy/core.py
cuepy/engine.py
cuepy/gpu_detect.py
cuepy/gpu_pool.py
cuepy/job_queue.py
cuepy/job_runner.py
cuepy/scheduler.py
cuepy/system.py
cue_ml-1.0.0.dist-info/METADATA
cue_ml-1.0.0.dist-info/WHEEL
cue_ml-1.0.0.dist-info/entry_points.txt
cue_ml-1.0.0.dist-info/top_level.txt
cue_ml-1.0.0.dist-info/RECORD
