Metadata-Version: 2.4
Name: cue-ml
Version: 1.0.0
Summary: A streamlined workload manager designed for Deep Learning research, optimizing GPU usage for individuals and small teams.
Home-page: https://github.com/Sureshmohan19/cue-ml
Author: Suresh Neethimohan
Author-email: mohansuresh333@gmail.com
License: MIT
Classifier: License :: OSI Approved :: MIT License
Classifier: Programming Language :: Python :: 3
Classifier: Programming Language :: Python :: 3.10
Classifier: Programming Language :: Python :: 3.11
Classifier: Topic :: System :: Distributed Computing
Requires-Python: >=3.10.0
License-File: LICENSE
Requires-Dist: PyYAML>=6.0
Provides-Extra: test
Requires-Dist: pytest>=7.0; extra == "test"
Requires-Dist: pytest-cov; extra == "test"
Provides-Extra: dev
Requires-Dist: black; extra == "dev"
Requires-Dist: isort; extra == "dev"
Requires-Dist: twine; extra == "dev"
Requires-Dist: wheel; extra == "dev"
Dynamic: author
Dynamic: author-email
Dynamic: classifier
Dynamic: description
Dynamic: description-content-type
Dynamic: home-page
Dynamic: license
Dynamic: license-file
Dynamic: provides-extra
Dynamic: requires-dist
Dynamic: requires-python
Dynamic: summary
